imdb_cli_tool/__init__.py
imdb_cli_tool/imdb_actor_search.py
imdb_cli_tool-1.0.1.dist-info/METADATA
imdb_cli_tool-1.0.1.dist-info/RECORD
imdb_cli_tool-1.0.1.dist-info/WHEEL
imdb_cli_tool-1.0.1.dist-info/top_level.txt
