Metadata-Version: 2.1
Name: imdb-cli-tool
Version: 1.0.1
Summary: A cli tool to pull movie information about actors/actresses.
Home-page: https://github.com/Zocozoro/imdb
Author: Zak Cook
Author-email: 1zrcook@gmail.com
License: UNKNOWN
Platform: UNKNOWN
Classifier: Programming Language :: Python :: 3
Classifier: License :: OSI Approved :: MIT License
Classifier: Operating System :: OS Independent
Requires-Dist: IMDbPY
